vardict/LICENSE.txt
vardict/__init__.py
vardict/vardict.py
vardict-1.0.3.dist-info/METADATA
vardict-1.0.3.dist-info/WHEEL
vardict-1.0.3.dist-info/top_level.txt
vardict-1.0.3.dist-info/RECORD
