Metadata-Version: 2.4
Name: vardict
Version: 1.0.3
Summary: vardict - dict with variables
Author-email: Ruud van der Ham <rt.van.der.ham@gmail.com>
Project-URL: Homepage, https://github.com/salabim/vardict
Project-URL: Repository, https://github.com/salabim/vardict
Classifier: Development Status :: 5 - Production/Stable
Classifier: License :: OSI Approved :: MIT License
Classifier: Programming Language :: Python :: 3 :: Only
Requires-Python: >=3.9
Requires-Dist: executing>=2.2.0
